simplemind_ng/__init__.py
simplemind_ng/logging.py
simplemind_ng/models.py
simplemind_ng/settings.py
simplemind_ng/utils.py
simplemind_ng/providers/__init__.py
simplemind_ng/providers/_base.py
simplemind_ng/providers/_base_tools.py
simplemind_ng/providers/amazon.py
simplemind_ng/providers/anthropic.py
simplemind_ng/providers/deepseek.py
simplemind_ng/providers/gemini.py
simplemind_ng/providers/groq.py
simplemind_ng/providers/ollama.py
simplemind_ng/providers/openai.py
simplemind_ng/providers/xai.py
simplemind_ng-0.5.1.dist-info/METADATA
simplemind_ng-0.5.1.dist-info/WHEEL
simplemind_ng-0.5.1.dist-info/licenses/LICENSE
simplemind_ng-0.5.1.dist-info/RECORD
