Metadata-Version: 2.4
Name: simplemind-ng
Version: 0.5.1
Summary: A maintained next-generation fork of simplemind with ongoing development and modern LLM features.
Project-URL: Homepage, https://github.com/jparr721/simplemind-ng
Project-URL: Source, https://github.com/jparr721/simplemind-ng
Project-URL: Issues, https://github.com/jparr721/simplemind-ng/issues
License-File: LICENSE
Requires-Python: >=3.10
Requires-Dist: instructor
Requires-Dist: logfire
Requires-Dist: pydantic
Requires-Dist: pydantic-settings
Provides-Extra: amazon
Requires-Dist: anthropic; extra == 'amazon'
Requires-Dist: boto3; extra == 'amazon'
Requires-Dist: botocore; extra == 'amazon'
Provides-Extra: anthropic
Requires-Dist: anthropic; extra == 'anthropic'
Provides-Extra: deepseek
Requires-Dist: openai; extra == 'deepseek'
Provides-Extra: full
Requires-Dist: anthropic; extra == 'full'
Requires-Dist: boto3; extra == 'full'
Requires-Dist: botocore; extra == 'full'
Requires-Dist: google-genai; extra == 'full'
Requires-Dist: groq; extra == 'full'
Requires-Dist: openai; extra == 'full'
Provides-Extra: gemini
Requires-Dist: google-genai; extra == 'gemini'
Provides-Extra: groq
Requires-Dist: groq; extra == 'groq'
Provides-Extra: ollama
Requires-Dist: openai; extra == 'ollama'
Provides-Extra: openai
Requires-Dist: openai; extra == 'openai'
Provides-Extra: xai
Requires-Dist: openai; extra == 'xai'
